databricks_sqlalchemy_oauth/__init__.py
databricks_sqlalchemy_oauth/connection_builder.py
databricks_sqlalchemy_oauth-0.1.0.dist-info/METADATA
databricks_sqlalchemy_oauth-0.1.0.dist-info/WHEEL
databricks_sqlalchemy_oauth-0.1.0.dist-info/RECORD
